utic_dev_tools/__init__.py
utic_dev_tools/plugins/__init__.py
utic_dev_tools/plugins/cli.py
utic_dev_tools/plugins/icon_converter/README.md
utic_dev_tools/plugins/icon_converter/__init__.py
utic_dev_tools/plugins/icon_converter/cli.py
utic_dev_tools/plugins/icon_converter/convert.py
utic_dev_tools/plugins/icon_converter/errors.py
utic_dev_tools/plugins/icon_converter/converters/__init__.py
utic_dev_tools/plugins/icon_converter/converters/base.py
utic_dev_tools/plugins/icon_converter/converters/svg.py
utic_dev_tools/plugins/icon_converter/mixins/__init__.py
utic_dev_tools/plugins/icon_converter/mixins/base64.py
utic_dev_tools/plugins/icon_converter/models/icon.py
utic_dev_tools/plugins/plugin_cookiecutter/cookiecutter.json
utic_dev_tools/plugins/plugin_cookiecutter/hooks/pre_gen_project.py
utic_dev_tools/plugins/plugin_cookiecutter/plugin-{{cookiecutter.type}}-{{cookiecutter.subtype}}/Dockerfile
utic_dev_tools/plugins/plugin_cookiecutter/plugin-{{cookiecutter.type}}-{{cookiecutter.subtype}}/Makefile
utic_dev_tools/plugins/plugin_cookiecutter/plugin-{{cookiecutter.type}}-{{cookiecutter.subtype}}/README.md
utic_dev_tools/plugins/plugin_cookiecutter/plugin-{{cookiecutter.type}}-{{cookiecutter.subtype}}/pyproject.toml
utic_dev_tools/plugins/plugin_cookiecutter/plugin-{{cookiecutter.type}}-{{cookiecutter.subtype}}/settings.json
utic_dev_tools/plugins/plugin_cookiecutter/plugin-{{cookiecutter.type}}-{{cookiecutter.subtype}}/src/plugin_{{cookiecutter.type}}_{{cookiecutter.subtype}}/__init__.py
utic_dev_tools/plugins/plugin_cookiecutter/plugin-{{cookiecutter.type}}-{{cookiecutter.subtype}}/tests/test_plugin.py
utic_dev_tools-0.2.9.dist-info/METADATA
utic_dev_tools-0.2.9.dist-info/WHEEL
utic_dev_tools-0.2.9.dist-info/entry_points.txt
utic_dev_tools-0.2.9.dist-info/RECORD
