Metadata-Version: 2.4
Name: utic-dev-tools
Version: 0.2.9
Summary: Dev tools for Unstructured.io ecosystem.
Requires-Python: >=3.12
Requires-Dist: orjson
Requires-Dist: pydantic
Requires-Dist: requests
Requires-Dist: scour>=0.38.2
Requires-Dist: utic-public-types>=3.0.0
